illufly/__PROMPT_TEMPLATES__/CODE/DATASET_SUMMARY/main.mu
illufly/__PROMPT_TEMPLATES__/CODE/Matplot/main.mu
illufly/__PROMPT_TEMPLATES__/CODE/Pandas/main.mu
illufly/__PROMPT_TEMPLATES__/FLOW/CoT/Planner/main.mu
illufly/__PROMPT_TEMPLATES__/FLOW/CoT/SubTask/main.mu
illufly/__PROMPT_TEMPLATES__/FLOW/PlanAndSolve/Planner/example.mu
illufly/__PROMPT_TEMPLATES__/FLOW/PlanAndSolve/Planner/main.mu
illufly/__PROMPT_TEMPLATES__/FLOW/PlanAndSolve/RePlanner/main.mu
illufly/__PROMPT_TEMPLATES__/FLOW/PlanAndSolve/Worker/main.mu
illufly/__PROMPT_TEMPLATES__/FLOW/ReAct/Planner/main.mu
illufly/__PROMPT_TEMPLATES__/FLOW/ReAct/SubTask/main.mu
illufly/__PROMPT_TEMPLATES__/FLOW/ReWOO/Planner/main.mu
illufly/__PROMPT_TEMPLATES__/FLOW/ReWOO/Solver/main.mu
illufly/__PROMPT_TEMPLATES__/FLOW/Scribe/main.mu
illufly/__PROMPT_TEMPLATES__/RAG/QA_GEN/main.mu
illufly/__PROMPT_TEMPLATES__/RAG/Q_GEN/main.mu
illufly/__PROMPT_TEMPLATES__/TOOLS_CALLING/main.mu
illufly/__PROMPT_TEMPLATES__/WRITER/FromOutline/main.mu
illufly/__PROMPT_TEMPLATES__/WRITER/IDEA/main.mu
illufly/__PROMPT_TEMPLATES__/WRITER/OUTLINE/example.mu
illufly/__PROMPT_TEMPLATES__/WRITER/OUTLINE/main.mu
illufly/__init__.py
illufly/__version__.py
illufly/chat/__init__.py
illufly/chat/fake/__init__.py
illufly/chat/fake/chat.py
illufly/community/__init__.py
illufly/community/dashscope/__init__.py
illufly/community/dashscope/embeddings.py
illufly/community/dashscope/qwen.py
illufly/community/dashscope/reranker.py
illufly/community/dashscope/wanx.py
illufly/community/faiss/__init__.py
illufly/community/faiss/faiss_cpu.py
illufly/community/http.py
illufly/community/hugging_face/__init__.py
illufly/community/hugging_face/embeddings.py
illufly/community/openai/__init__.py
illufly/community/openai/chat.py
illufly/community/openai/embeddings.py
illufly/community/zhipu/__init__.py
illufly/community/zhipu/cogvideox.py
illufly/community/zhipu/cogview.py
illufly/community/zhipu/embeddings.py
illufly/community/zhipu/glm4.py
illufly-0.6.1.dist-info/LICENSE
illufly-0.6.1.dist-info/METADATA
illufly-0.6.1.dist-info/WHEEL
illufly-0.6.1.dist-info/RECORD
