Metadata-Version: 2.1
Name: illufly
Version: 0.6.1
Summary: A simple Agent framework based on GPT with auto-evolution ability.
Home-page: https://github.com/arcstep/illufly
License: MIT
Author: arcstep
Author-email: xuehongwei@illufly.com
Requires-Python: >=3.10,<4
Classifier: License :: OSI Approved :: MIT License
Classifier: Programming Language :: Python :: 3
Classifier: Programming Language :: Python :: 3.10
Classifier: Programming Language :: Python :: 3.11
Classifier: Programming Language :: Python :: 3.12
Requires-Dist: aiohttp (>=3.10.10,<4.0.0)
Requires-Dist: asyncio (>=3.4.3,<4.0.0)
Requires-Dist: chevron (>=0.14.0,<0.15.0)
Requires-Dist: faiss-cpu (>=1.8.0.post1,<2.0.0)
Requires-Dist: fastapi (>=0.111.0,<0.112.0)
Requires-Dist: matplotlib (>=3.9.2,<4.0.0)
Requires-Dist: mistune (>=3.0.2,<4.0.0)
Requires-Dist: numpy (>=2.1.3,<3.0.0)
Requires-Dist: pandas (>=2.2.2,<3.0.0)
Requires-Dist: python-jose (>=3.3.0,<4.0.0)
Requires-Dist: scipy (>=1.14.1,<2.0.0)
Requires-Dist: seaborn (>=0.13.2,<0.14.0)
Requires-Dist: tabulate (>=0.9.0,<0.10.0)
Requires-Dist: tiktoken (>=0.7.0,<0.8.0)
Project-URL: Repository, https://github.com/arcstep/illufly.git
